MANIFEST.in
README.rst
pyproject.toml
setup.cfg
setup.py
docs/Makefile
docs/conf.py
docs/contributing.rst
docs/data.rst
docs/history.rst
docs/index.rst
docs/installation.rst
docs/make.bat
docs/model.rst
docs/modules.rst
docs/readme.rst
docs/usage.rst
docs/_build/html/_static/file.png
docs/_build/html/_static/minus.png
docs/_build/html/_static/plus.png
src/deoxys/__init__.py
src/deoxys.egg-info/PKG-INFO
src/deoxys.egg-info/SOURCES.txt
src/deoxys.egg-info/dependency_links.txt
src/deoxys.egg-info/requires.txt
src/deoxys.egg-info/top_level.txt
src/deoxys/automation/__init__.py
src/deoxys/automation/architecture.py
src/deoxys/automation/data.py
src/deoxys/customize/__init__.py
src/deoxys/data/__init__.py
src/deoxys/data/data_generator.py
src/deoxys/data/data_reader.py
src/deoxys/data/preprocessor.py
src/deoxys/database/__init__.py
src/deoxys/database/dbclient.py
src/deoxys/database/dbconst.py
src/deoxys/experiment/__init__.py
src/deoxys/experiment/multi_experiment.py
src/deoxys/experiment/pipeline.py
src/deoxys/experiment/postprocessor.py
src/deoxys/experiment/single_experiment.py
src/deoxys/keras/__init__.py
src/deoxys/keras/activations.py
src/deoxys/keras/backend.py
src/deoxys/keras/callbacks.py
src/deoxys/keras/layers.py
src/deoxys/keras/losses.py
src/deoxys/keras/metrics.py
src/deoxys/keras/models.py
src/deoxys/keras/optimizers.py
src/deoxys/keras/preprocessing.py
src/deoxys/keras/utils.py
src/deoxys/loaders/__init__.py
src/deoxys/loaders/architecture.py
src/deoxys/loaders/data_loader.py
src/deoxys/loaders/params.py
src/deoxys/loaders/train_params.py
src/deoxys/model/__init__.py
src/deoxys/model/activations.py
src/deoxys/model/callbacks.py
src/deoxys/model/layers.py
src/deoxys/model/losses.py
src/deoxys/model/metrics.py
src/deoxys/model/model.py
src/deoxys/model/optimizers.py
src/deoxys/utils/__init__.py
src/deoxys/utils/data_utils.py
src/deoxys/utils/file_utils.py
src/deoxys/utils/json_utils.py
src/deoxys/utils/singleton.py
tests/__init__.py
tests/automation/test_auto_architecture.py
tests/data/test_datareader.py
tests/data/test_preprocessor.py
tests/experiment/test_single_experiment.py
tests/h5_files/model.002.h5
