Metadata-Version: 1.1
Name: deoxys
Version: 0.0.11
Summary: Keras-based framework for UNet structure in Cancer Tumor Delineation
Home-page: https://github.com/huynhngoc/deoxys
Author: Ngoc Huynh Bao
Author-email: ngoc.huynh.bao@nmbu.no
License: "MIT license",
Keywords: deoxys
Platform: UNKNOWN
Classifier: Intended Audience :: Developers
Classifier: License :: OSI Approved :: MIT License
Classifier: Natural Language :: English
Classifier: Programming Language :: Python :: 3.7
